{
    "color": {
      "primary": {
        "50": { "value": "#F3F8FF", "comment": "@tokens ColorPrimary\n* @presenter Color" },
        "100": { "value": "#E7F0FE" },
        "200": { "value": "#CEE2FE" },
        "300": { "value": "#9DC4FD" },
        "400": { "value": "#79AEFC" },
        "500": { "value": "#609FFB" },
        "600": { "value": "#4891FB" },
        "700": { "value": "#3082FA" },
        "800": { "value": "#0B6CF9" },
        "900": { "value": "#0666F4" },
  
        "50i": { "value": "#162354", "comment": "@tokens ColorPrimaryInverse\n* @presenter Color" },
        "100i": { "value": "#192F68" },
        "200i": { "value": "#1D3A7B" },
        "300i": { "value": "#20468F" },
        "400i": { "value": "#2451A2" },
        "500i": { "value": "#275DB6" },
        "600i": { "value": "#2A68C9" },
        "700i": { "value": "#2E74DD" },
        "800i": { "value": "#317FF0" },
        "900i": { "value": "#3D8BFC" }
      }
    }
  
    "color": {
      "secondary": {
        "50": { "value": "#F3F4F6", "comment": "@tokens ColorSecondary\n* @presenter Color" },
        "100": { "value": "#ECEFF1" },
        "200": { "value": "#E0E4E8" },
        "300": { "value": "#CDD3DB" },
        "400": { "value": "#BBC3CD" },
        "500": { "value": "#AEB8C4" },
        "600": { "value": "#9BA7B7" },
        "700": { "value": "#8F9CAE" },
        "800": { "value": "#8291A5" },
        "900": { "value": "#67788E" },
  
        "50i": { "value": "#2D3253", "comment": "@tokens ColorSecondaryInverse\n* @presenter Color" },
        "100i": { "value": "#3A405F" },
        "200i": { "value": "#464D6B" },
        "300i": { "value": "#535B76" },
        "400i": { "value": "#606882" },
        "500i": { "value": "#6C768E" },
        "600i": { "value": "#79839A" },
        "700i": { "value": "#8691A5" },
        "800i": { "value": "#929EB1" },
        "900i": { "value": "#9FACBD" }
      }
    }
  
    "color": {
      "success": {
        "50": { "value": "#F2FBF6", "comment": "@tokens ColorSuccess\n* @presenter Color" },
        "100": { "value": "#D9F3E5" },
        "200": { "value": "#BFEBD3" },
        "300": { "value": "#99DFB9" },
        "400": { "value": "#73D49F" },
        "500": { "value": "#59CC8D" },
        "600": { "value": "#33C073" },
        "700": { "value": "#1AB862" },
        "800": { "value": "#00B050" },
        "900": { "value": "#00853C  " },
  
        "50i": { "value": "#0E3638", "comment": "@tokens ColorSuccessInverse\n* @presenter Color" },
        "100i": { "value": "#0C4C38" },
        "200i": { "value": "#0B6337" },
        "300i": { "value": "#097937" },
        "400i": { "value": "#088F36" },
        "500i": { "value": "#06A636" },
        "600i": { "value": "#05BC35" },
        "700i": { "value": "#03D235" },
        "800i": { "value": "#02E934" },
        "900i": { "value": "#00FF34" }
      }
    }
  
    "color": {
      "danger": {
        "50": { "value": "#FFF2F2", "comment": "@tokens ColorDanger\n* @presenter Color" },
        "100": { "value": "#FFD9D9" },
        "200": { "value": "#FFBFBF" },
        "300": { "value": "#FF9999" },
        "400": { "value": "#FF7373" },
        "500": { "value": "#FF5959" },
        "600": { "value": "#FF3333" },
        "700": { "value": "#FF1A1A" },
        "800": { "value": "#FF0000" },
        "900": { "value": "#CC0000" },
  
        "50i": { "value": "#341D3D", "comment": "@tokens ColorDangerInverse\n* @presenter Color" },
        "100i": { "value": "#4A2340" },
        "200i": { "value": "#602942" },
        "300i": { "value": "#762F45" },
        "400i": { "value": "#8C3547" },
        "500i": { "value": "#A13C4A" },
        "600i": { "value": "#B7424C" },
        "700i": { "value": "#CD484F" },
        "800i": { "value": "#E34E51" },
        "900i": { "value": "#F95454" }
      }
    }
  
    "color": {
      "warning": {
        "50": { "value": "#FFFBF3", "comment": "@tokens ColorWarning\n* @presenter Color" },
        "100": { "value": "#FEF4D9" },
        "200": { "value": "#FEEDC0" },
        "300": { "value": "#FDE29B" },
        "400": { "value": "#FCD775" },
        "500": { "value": "#FBD05C" },
        "600": { "value": "#FAC536" },
        "700": { "value": "#FABD1D" },
        "800": { "value": "#F9B604" },
        "900": { "value": "#B47516" },
  
        "50i": { "value": "#342B31", "comment": "@tokens ColorWarningInverse\n* @presenter Color" },
        "100i": { "value": "#4A3A2C" },
        "200i": { "value": "#604A27" },
        "300i": { "value": "#765922" },
        "400i": { "value": "#8C691D" },
        "500i": { "value": "#A17818" },
        "600i": { "value": "#B78813" },
        "700i": { "value": "#CD970E" },
        "800i": { "value": "#E3A709" },
        "900i": { "value": "#F9B604 " }
      }
    }
  
    "color": {
      "info": {
        "50": { "value": "#F4FBFF", "comment": "@tokens ColorInfo\n* @presenter Color" },
        "100": { "value": "#DEF3FF" },
        "200": { "value": "#DEF3FF" },
        "300": { "value": "#A7DFFF" },
        "400": { "value": "#85D4FF" },
        "500": { "value": "#6FCCFF" },
        "600": { "value": "#4EC0FF" },
        "700": { "value": "#38B8FF" },
        "800": { "value": "#22B0FF" },
        "900": { "value": "#027CC0" },
  
        "50i": { "value": "#142E57", "comment": "@tokens ColorInfoInverse\n* @presenter Color" },
        "100i": { "value": "#163F6A" },
        "200i": { "value": "#17517C" },
        "300i": { "value": "#19628F" },
        "400i": { "value": "#1A73A2" },
        "500i": { "value": "#1C85B4" },
        "600i": { "value": "#1D96C7" },
        "700i": { "value": "#1FA7DA" },
        "800i": { "value": "#20B9EC" },
        "900i": { "value": "#22CAFF" }
      }
    }
  
    "color": {
      "neutral": {
        "50": { "value": "#FFFFFF", "comment": "@tokens ColorNeutral\n* @presenter Color" },
        "100": { "value": "#E3E3E3" },
        "200": { "value": "#C6C6C6" },
        "300": { "value": "#AAAAAA" },
        "400": { "value": "#8E8E8E" },
        "500": { "value": "#717171" },
        "600": { "value": "#555555" },
        "700": { "value": "#393939" },
        "800": { "value": "#1C1C1C" },
        "900": { "value": "#000000 " },
  
        "50i": { "value": "#000000", "comment": "@tokens ColorNeutralInverse\n* @presenter Color" },
        "100i": { "value": "#1C1C1C" },
        "200i": { "value": "#393939" },
        "300i": { "value": "#555555" },
        "400i": { "value": "#717171" },
        "500i": { "value": "#8E8E8E" },
        "600i": { "value": "#AAAAAA" },
        "700i": { "value": "#C6C6C6" },
        "800i": { "value": "#E3E3E3" },
        "900i": { "value": "#FFFFFF" }
      }
    }
  
    "color": {
      "background": {
        "50": { "value": "#FFFFFF", "comment": "@tokens ColorBackground\n* @presenter Color" },
        "100": { "value": "#F5F6F7" },
        "200": { "value": "#F0F4F9" },
        "300": { "value": "#E9EEF4" },
        "400": { "value": "#DBE2EB" },
  
        "50i": {
          "value": "#000000",
          "comment": "@tokens ColorBackgroundInverse\n* @presenter Color"
        },
        "100i": { "value": "#111339" },
        "200i": { "value": "#282F5D" },
        "300i": { "value": "#353B61" },
        "400i": { "value": "#484C68" }
      }
    }
  }
        